sippers/__init__.py
sippers/exceptions.py
sippers/file.py
sippers/logging.py
sippers/utils.py
sippers/adapters/__init__.py
sippers/adapters/cnmc.py
sippers/adapters/cnmc_gas.py
sippers/adapters/cnmc_v2.py
sippers/adapters/endesa.py
sippers/adapters/hidrocantabrico.py
sippers/adapters/iberdrola.py
sippers/backends/__init__.py
sippers/backends/base.py
sippers/backends/mongodb.py
sippers/cli/__init__.py
sippers/data/hc_poblacions.json
sippers/models/__init__.py
sippers/models/cnmc.py
sippers/models/cnmc_gas.py
sippers/models/cnmc_v2.py
sippers/models/endesa.py
sippers/models/hidrocantabrico.py
sippers/models/iberdrola.py
sippers/parsers/__init__.py
sippers/parsers/cnmc.py
sippers/parsers/cnmc_gas.py
sippers/parsers/cnmc_v2.py
sippers/parsers/endesa.py
sippers/parsers/hidrocantabrico.py
sippers/parsers/iberdrola.py
sippers/parsers/parser.py
tests/__init__.py
tests/test_adapters.py
tests/test_backend.py
tests/test_data.py
tests/tests_detection.py
tests/tests_file.py
tests/tests_logging.py
tests/tests_parsers.py
sippers-2.4.1.dist-info/LICENSE
sippers-2.4.1.dist-info/METADATA
sippers-2.4.1.dist-info/WHEEL
sippers-2.4.1.dist-info/entry_points.txt
sippers-2.4.1.dist-info/top_level.txt
sippers-2.4.1.dist-info/RECORD
