Metadata-Version: 2.1
Name: sippers
Version: 2.4.1
Summary: sippers
Home-page: https://github.com/gisce/sippers
Author: GISCE-TI, S.L.
Author-email: devel@gisce.net
License: GPLv3
License-File: LICENSE
Requires-Dist: pymongo<=3.13.0
Requires-Dist: osconf
Requires-Dist: marshmallow<3.0
Requires-Dist: click
Requires-Dist: raven<6.0.0; python_version <= "2.7.18"
Requires-Dist: raven; python_version > "2.7.18"
